telebot/__init__.py
telebot-0.0.4.dist-info/LICENSE
telebot-0.0.4.dist-info/METADATA
telebot-0.0.4.dist-info/WHEEL
telebot-0.0.4.dist-info/top_level.txt
telebot-0.0.4.dist-info/RECORD
