Metadata-Version: 1.1
Name: telebot
Version: 0.0.4
Summary: A Telegram bot library, with simple route decorators.
Home-page: https://github.com/KyleJamesWalker/telebot
Author: Kyle James Walker
Author-email: KyleJamesWalker@gmail.com
License: MIT
Platform: UNKNOWN
Classifier: Development Status :: 2 - Pre-Alpha
Classifier: Intended Audience :: Developers
Classifier: License :: OSI Approved :: MIT License
Classifier: Natural Language :: English
Classifier: Programming Language :: Python :: 2.7
Classifier: Programming Language :: Python :: 3.5
